odoo/addons/hr_timesheet_sheet_activity/README.rst
odoo/addons/hr_timesheet_sheet_activity/__init__.py
odoo/addons/hr_timesheet_sheet_activity/__manifest__.py
odoo/addons/hr_timesheet_sheet_activity/data/hr_timesheet_sheet_activity_data.xml
odoo/addons/hr_timesheet_sheet_activity/i18n/es.po
odoo/addons/hr_timesheet_sheet_activity/i18n/hr_timesheet_sheet_activity.pot
odoo/addons/hr_timesheet_sheet_activity/i18n/it.po
odoo/addons/hr_timesheet_sheet_activity/i18n/nl_NL.po
odoo/addons/hr_timesheet_sheet_activity/i18n/pt.po
odoo/addons/hr_timesheet_sheet_activity/models/__init__.py
odoo/addons/hr_timesheet_sheet_activity/models/hr_timesheet_sheet.py
odoo/addons/hr_timesheet_sheet_activity/readme/CONTRIBUTORS.rst
odoo/addons/hr_timesheet_sheet_activity/readme/DESCRIPTION.rst
odoo/addons/hr_timesheet_sheet_activity/static/description/icon.png
odoo/addons/hr_timesheet_sheet_activity/static/description/index.html
odoo/addons/hr_timesheet_sheet_activity/tests/__init__.py
odoo/addons/hr_timesheet_sheet_activity/tests/test_hr_timesheet_sheet_activity.py
odoo/addons/hr_timesheet_sheet_activity/views/mail_activity.xml
odoo14_addon_hr_timesheet_sheet_activity-14.0.1.0.1.dev11.dist-info/METADATA
odoo14_addon_hr_timesheet_sheet_activity-14.0.1.0.1.dev11.dist-info/WHEEL
odoo14_addon_hr_timesheet_sheet_activity-14.0.1.0.1.dev11.dist-info/top_level.txt
odoo14_addon_hr_timesheet_sheet_activity-14.0.1.0.1.dev11.dist-info/RECORD
